enchantx/__init__.py
enchantx/vectorizer/__init__.py
EnchantX-0.1.dist-info/METADATA
EnchantX-0.1.dist-info/WHEEL
EnchantX-0.1.dist-info/top_level.txt
EnchantX-0.1.dist-info/RECORD
