Metadata-Version: 2.1
Name: EnchantX
Version: 0.1
Summary: An extension of PyEnchant Wrapper
Home-page: https://github.com/akashdve/enchantx
Author: AkashD
Author-email: akashdave555@gmail.com
License: UNKNOWN
Platform: UNKNOWN
Requires-Python: >=3.6
